crawlsy_spider/__init__.py
crawlsy_spider/cli.py
crawlsy_spider/craw.py
crawlsy_spider-0.1.2.dist-info/LICENSE
crawlsy_spider-0.1.2.dist-info/METADATA
crawlsy_spider-0.1.2.dist-info/WHEEL
crawlsy_spider-0.1.2.dist-info/entry_points.txt
crawlsy_spider-0.1.2.dist-info/RECORD
