Metadata-Version: 2.3
Name: crawlsy-spider
Version: 0.1.2
Summary: 
Author: YUNHAI
Author-email: bybxbwg@foxmail.com
Requires-Python: >=3.9,<4.0
Classifier: Programming Language :: Python :: 3
Classifier: Programming Language :: Python :: 3.9
Classifier: Programming Language :: Python :: 3.10
Classifier: Programming Language :: Python :: 3.11
Classifier: Programming Language :: Python :: 3.12
Classifier: Programming Language :: Python :: 3.13
Requires-Dist: rq (>=2.1.0,<3.0.0)
